Metadata-Version: 2.1
Name: cch_algorithms
Version: 0.0.1
Summary: Machine learning algorithms
Home-page: https://dev.azure.com/yalecch/cch-research
Author: Center for Computational Health
Author-email: wade.schulz@yale.edu
Project-URL: Repository, https://dev.azure.com/yalecch/cch-research/_git/cch-algorithms
Classifier: Programming Language :: Python :: 3
Classifier: Operating System :: OS Independent
Requires-Python: >=3.9
Requires-Dist: mlflow
Requires-Dist: matplotlib
Requires-Dist: numpy
Requires-Dist: pandas
Requires-Dist: qiskit-aer
Requires-Dist: qiskit-ibm-runtime
Requires-Dist: qiskit-machine-learning
Requires-Dist: scikit-learn
Requires-Dist: scikit-learn
Requires-Dist: tqdm
Requires-Dist: urllib3
Requires-Dist: xgboost
